ctxdb/README.rst
ctxdb/__init__.py
ctxdb/ctxdb/__init__.py
ctxdb/ctxdb/api/routes.py
ctxdb/ctxdb/core/__init__.py
ctxdb/ctxdb/core/config.py
ctxdb/ctxdb/core/ctxdb.py
ctxdb/ctxdb/models/__init__.py
ctxdb/ctxdb/models/context.py
ctxdb/ctxdb/models/index.py
ctxdb/ctxdb/models/namespace.py
ctxdb/ctxdb/models/workspace.py
ctxdb/ctxdb/utils/__init__.py
ctxdb/examples/__init__.py
ctxdb/examples/example_usage.py
ctxdb/main.py
ctxdb/pyproject.toml
ctxdb/tests/__init__.py
ctxdb/tests/test_ctxdb.py
ctxdb-0.0.1.dist-info/WHEEL
ctxdb-0.0.1.dist-info/METADATA
ctxdb-0.0.1.dist-info/RECORD
