Metadata-Version: 2.1
Name: ctxdb
Version: 0.0.1
Summary: 
Author: Philip Solarz
Author-email: philipsolarz@outlook.com
Requires-Python: >=3.10.0,<3.11
Classifier: Programming Language :: Python :: 3
Classifier: Programming Language :: Python :: 3.10
Requires-Dist: Flask (>=2.2.0,<3.0.0)
Requires-Dist: docarray[redis] (>=0.37.0,<0.38.0)
Requires-Dist: fastapi (>=0.101.1,<0.102.0)
Requires-Dist: numpy (>=1.22.2,<2.0.0)
Requires-Dist: sentence-transformers (>=2.2.2,<3.0.0)
Requires-Dist: uvicorn (>=0.23.2,<0.24.0)
